datahen/API.py
datahen/CLI.py
datahen/Executor.py
datahen/Exports.py
datahen/GlobalPages.py
datahen/Helpers.py
datahen/JobPages.py
datahen/Jobs.py
datahen/ScraperJobPages.py
datahen/ScraperJobs.py
datahen/Scrapers.py
datahen/__init__.py
datahen-0.4.dist-info/LICENSE
datahen-0.4.dist-info/METADATA
datahen-0.4.dist-info/WHEEL
datahen-0.4.dist-info/entry_points.txt
datahen-0.4.dist-info/top_level.txt
datahen-0.4.dist-info/RECORD
